Metadata-Version: 2.1
Name: FoxySheep
Version: 1.2.3
Summary: Mathematica parser and translator
Home-page: http://github.com/rocky/FoxySheep2
Author: Robert Jacobson
License: UNKNOWN
Platform: UNKNOWN
Classifier: Programming Language :: Python :: 3.6
Classifier: Programming Language :: Python :: 3.7
Classifier: Programming Language :: Python :: 3.8
Requires-Dist: antlr4-python3-runtime (<4.8,>=4.7)
Requires-Dist: click (>=7.1.2)
Requires-Dist: astor
Requires-Dist: PyYAML
Requires-Dist: astpretty
